<annotation>
<folder>MULTITASK</folder>
<filename>111.jpg</filename>
<source>
<database>LOGODetection</database>
<annotation>LIUPANSHU</annotation>
<image>flickr</image>
<flickrid>NULL</flickrid>
</source>
<owner>
<flickrid>NULL</flickrid>
<name>SyGoing</name>
</owner>
<size>
<width>640</width>
<height>426</height>
<depth>3</depth>
</size>
<segmented>0</segmented>
<object>
<name>plate</name>
<pose>Unspecified</pose>
<truncated>0</truncated>
<difficult>0</difficult>
<bndbox>
<xmin>265</xmin>
<ymin>186</ymin>
<xmax>390</xmax>
<ymax>293</ymax>
</bndbox>
<lm>
<x0>275.207</x0>
<y0>231.256</y0>
<x1>370.248</x1>
<y1>198.198</y1>
<x2>377.686</x2>
<y2>232.083</y2>
<x3>288.43</x3>
<y3>280.843</y3>
</lm>
</object>
</annotation>
