<annotation>
<folder>MULTITASK</folder>
<filename>129.jpg</filename>
<source>
<database>LOGODetection</database>
<annotation>LIUPANSHU</annotation>
<image>flickr</image>
<flickrid>NULL</flickrid>
</source>
<owner>
<flickrid>NULL</flickrid>
<name>SyGoing</name>
</owner>
<size>
<width>620</width>
<height>464</height>
<depth>3</depth>
</size>
<segmented>0</segmented>
<object>
<name>plate</name>
<pose>Unspecified</pose>
<truncated>0</truncated>
<difficult>0</difficult>
<bndbox>
<xmin>63</xmin>
<ymin>57</ymin>
<xmax>497</xmax>
<ymax>450</ymax>
</bndbox>
<lm>
<x0>96.0</x0>
<y0>84.4</y0>
<x1>487.2</x1>
<y1>280.4</y1>
<x2>459.2</x2>
<y2>432.4</y2>
<x3>80.8</x3>
<y3>222.8</y3>
</lm>
</object>
</annotation>
