<annotation>
<folder>MULTITASK</folder>
<filename>140.jpg</filename>
<source>
<database>LOGODetection</database>
<annotation>LIUPANSHU</annotation>
<image>flickr</image>
<flickrid>NULL</flickrid>
</source>
<owner>
<flickrid>NULL</flickrid>
<name>SyGoing</name>
</owner>
<size>
<width>700</width>
<height>933</height>
<depth>3</depth>
</size>
<segmented>0</segmented>
<object>
<name>plate</name>
<pose>Unspecified</pose>
<truncated>0</truncated>
<difficult>0</difficult>
<bndbox>
<xmin>286</xmin>
<ymin>425</ymin>
<xmax>455</xmax>
<ymax>558</ymax>
</bndbox>
<lm>
<x0>308.955</x0>
<y0>490.299</y0>
<x1>432.09</x1>
<y1>434.328</y1>
<x2>429.104</x2>
<y2>479.851</y2>
<x3>307.463</x3>
<y3>543.284</y3>
</lm>
</object>
</annotation>
